{"route":{"hasTollRoad":false,"hasBridge":false,"boundingBox":{"lr":{"lng":16.453671,"lat":48.246391},"ul":{"lng":16.402002,"lat":48.2803}},"distance":4.047,"hasTimedRestriction":false,"hasTunnel":false,"hasHighway":false,"computedWaypoints":[],"routeError":{"errorCode":-400,"message":""},"formattedTime":"00:11:39","sessionId":"60684908-029b-4ee4-02b4-351c-12d3cb4bf26b","hasAccessRestriction":false,"realTime":-1,"hasSeasonalClosure":false,"hasCountryCross":false,"fuelUsed":0.24,"legs":[{"hasTollRoad":false,"hasBridge":false,"destNarrative":"Proceed to KAGRAN.","distance":4.047,"hasTimedRestriction":false,"hasTunnel":false,"hasHighway":false,"index":0,"formattedTime":"00:11:39","origIndex":-1,"hasAccessRestriction":false,"hasSeasonalClosure":false,"hasCountryCross":false,"roadGradeStrategy":[[]],"destIndex":4,"time":699,"hasUnpaved":false,"origNarrative":"","maneuvers":[{"distance":0.011,"streets":["B7","Brünner Straße","E461"],"narrative":"Start out going northeast on B7/Brünner Straße/E461 toward Carabelligasse.","turnType":0,"startPoint":{"lng":16.41094,"lat":48.280102},"index":0,"formattedTime":"00:00:01","directionName":"Northeast","maneuverNotes":[],"linkIds":[],"signs":[],"mapUrl":"http://www.mapquestapi.com/staticmap/v5/map?key=V5j8RGvth4UydnpUgMg2RYyVNpE12fJy&size=225,160&locations=48.28010177612305,16.410940170288086|marker-1||48.28024673461914,16.41103172302246|marker-2||&center=48.280174255371094,16.410985946655273&defaultMarker=none&zoom=15&rand=-1852306207&session=60684908-029b-4ee4-02b4-351c-12d3cb4bf26b","transportMode":"AUTO","attributes":0,"time":1,"iconUrl":"http://content.mqcdn.com/mqsite/turnsigns/icon-dirs-start_sm.gif","direction":3},{"distance":0.012,"streets":["Carabelligasse"],"narrative":"Turn left onto Carabelligasse.","turnType":6,"startPoint":{"lng":16.411032,"lat":48.280247},"index":1,"formattedTime":"00:00:16","directionName":"West","maneuverNotes":[],"linkIds":[],"signs":[],"mapUrl":"http://www.mapquestapi.com/staticmap/v5/map?key=V5j8RGvth4UydnpUgMg2RYyVNpE12fJy&size=225,160&locations=48.28024673461914,16.41103172302246|marker-2||48.28030014038086,16.410791397094727|marker-3||&center=48.2802734375,16.410911560058594&defaultMarker=none&zoom=15&rand=-1852306207&session=60684908-029b-4ee4-02b4-351c-12d3cb4bf26b","transportMode":"AUTO","attributes":0,"time":16,"iconUrl":"http://content.mqcdn.com/mqsite/turnsigns/rs_left_sm.gif","direction":7},{"distance":1.125,"streets":["B7","Brünner Straße"],"narrative":"Turn left onto B7/Brünner Straße/E461. Continue to follow B7/Brünner Straße.","turnType":6,"startPoint":{"lng":16.410791,"lat":48.2803},"index":2,"formattedTime":"00:03:05","directionName":"South","maneuverNotes":[],"linkIds":[],"signs":[],"mapUrl":"http://www.mapquestapi.com/staticmap/v5/map?key=V5j8RGvth4UydnpUgMg2RYyVNpE12fJy&size=225,160&locations=48.28030014038086,16.410791397094727|marker-3||48.26513671875,16.402002334594727|marker-4||&center=48.27271842956543,16.406396865844727&defaultMarker=none&zoom=9&rand=-1852306207&session=60684908-029b-4ee4-02b4-351c-12d3cb4bf26b","transportMode":"AUTO","attributes":0,"time":185,"iconUrl":"http://content.mqcdn.com/mqsite/turnsigns/rs_left_sm.gif","direction":4},{"distance":1.55,"streets":["B3"],"narrative":"Turn left onto B3/Katsushikastraße. Continue to follow B3.","turnType":6,"startPoint":{"lng":16.402002,"lat":48.265137},"index":3,"formattedTime":"00:03:30","directionName":"Southeast","maneuverNotes":[],"linkIds":[],"signs":[],"mapUrl":"http://www.mapquestapi.com/staticmap/v5/map?key=V5j8RGvth4UydnpUgMg2RYyVNpE12fJy&size=225,160&locations=48.26513671875,16.402002334594727|marker-4||48.2519645690918,16.427919387817383|marker-5||&center=48.2585506439209,16.414960861206055&defaultMarker=none&zoom=9&rand=-1852306207&session=60684908-029b-4ee4-02b4-351c-12d3cb4bf26b","transportMode":"AUTO","attributes":0,"time":210,"iconUrl":"http://content.mqcdn.com/mqsite/turnsigns/rs_left_sm.gif","direction":5},{"distance":0.73,"streets":["Donaufelder Straße"],"narrative":"Turn left onto Donaufelder Straße.","turnType":6,"startPoint":{"lng":16.427919,"lat":48.251965},"index":4,"formattedTime":"00:02:10","directionName":"East","maneuverNotes":[],"linkIds":[],"signs":[],"mapUrl":"http://www.mapquestapi.com/staticmap/v5/map?key=V5j8RGvth4UydnpUgMg2RYyVNpE12fJy&size=225,160&locations=48.2519645690918,16.427919387817383|marker-5||48.24996566772461,16.443326950073242|marker-6||&center=48.2509651184082,16.435623168945312&defaultMarker=none&zoom=10&rand=-1852306207&session=60684908-029b-4ee4-02b4-351c-12d3cb4bf26b","transportMode":"AUTO","attributes":0,"time":130,"iconUrl":"http://content.mqcdn.com/mqsite/turnsigns/rs_left_sm.gif","direction":8},{"distance":0.395,"streets":["Kagraner Platz"],"narrative":"Donaufelder Straße becomes Kagraner Platz.","turnType":0,"startPoint":{"lng":16.443327,"lat":48.249966},"index":5,"formattedTime":"00:01:02","directionName":"East","maneuverNotes":[],"linkIds":[],"signs":[],"mapUrl":"http://www.mapquestapi.com/staticmap/v5/map?key=V5j8RGvth4UydnpUgMg2RYyVNpE12fJy&size=225,160&locations=48.24996566772461,16.443326950073242|marker-6||48.248291015625,16.451400756835938|marker-7||&center=48.249128341674805,16.44736385345459&defaultMarker=none&zoom=11&rand=-1852306207&session=60684908-029b-4ee4-02b4-351c-12d3cb4bf26b","transportMode":"AUTO","attributes":0,"time":62,"iconUrl":"http://content.mqcdn.com/mqsite/turnsigns/rs_straight_sm.gif","direction":8},{"distance":0.064,"streets":["Zillingergasse"],"narrative":"Turn right onto Zillingergasse.","turnType":2,"startPoint":{"lng":16.451401,"lat":48.248291},"index":6,"formattedTime":"00:00:18","directionName":"Southeast","maneuverNotes":[],"linkIds":[],"signs":[],"mapUrl":"http://www.mapquestapi.com/staticmap/v5/map?key=V5j8RGvth4UydnpUgMg2RYyVNpE12fJy&size=225,160&locations=48.248291015625,16.451400756835938|marker-7||48.247474670410156,16.451570510864258|marker-8||&center=48.24788284301758,16.451485633850098&defaultMarker=none&zoom=14&rand=-1852306207&session=60684908-029b-4ee4-02b4-351c-12d3cb4bf26b","transportMode":"AUTO","attributes":0,"time":18,"iconUrl":"http://content.mqcdn.com/mqsite/turnsigns/rs_right_sm.gif","direction":5},{"distance":0.081,"streets":["Hirschstettner Straße"],"narrative":"Zillingergasse becomes Hirschstettner Straße.","turnType":0,"startPoint":{"lng":16.451571,"lat":48.247475},"index":7,"formattedTime":"00:00:20","directionName":"Southeast","maneuverNotes":[],"linkIds":[],"signs":[],"mapUrl":"http://www.mapquestapi.com/staticmap/v5/map?key=V5j8RGvth4UydnpUgMg2RYyVNpE12fJy&size=225,160&locations=48.247474670410156,16.451570510864258|marker-8||48.24639129638672,16.452171325683594|marker-9||&center=48.24693298339844,16.451870918273926&defaultMarker=none&zoom=13&rand=-1852306207&session=60684908-029b-4ee4-02b4-351c-12d3cb4bf26b","transportMode":"AUTO","attributes":0,"time":20,"iconUrl":"http://content.mqcdn.com/mqsite/turnsigns/rs_straight_sm.gif","direction":5},{"distance":0.079,"streets":[],"narrative":"Turn left.","turnType":6,"startPoint":{"lng":16.452171,"lat":48.246391},"index":8,"formattedTime":"00:00:57","directionName":"East","maneuverNotes":[],"linkIds":[],"signs":[],"mapUrl":"http://www.mapquestapi.com/staticmap/v5/map?key=V5j8RGvth4UydnpUgMg2RYyVNpE12fJy&size=225,160&locations=48.24639129638672,16.452171325683594|marker-9||48.24666213989258,16.453670501708984|marker-10||&center=48.24652671813965,16.45292091369629&defaultMarker=none&zoom=15&rand=-1852306207&session=60684908-029b-4ee4-02b4-351c-12d3cb4bf26b","transportMode":"AUTO","attributes":0,"time":57,"iconUrl":"http://content.mqcdn.com/mqsite/turnsigns/rs_left_sm.gif","direction":8},{"distance":0,"streets":[],"narrative":"KAGRAN.","turnType":-1,"startPoint":{"lng":16.453671,"lat":48.246662},"index":9,"formattedTime":"00:00:00","directionName":"","maneuverNotes":[],"linkIds":[],"signs":[],"transportMode":"AUTO","attributes":0,"time":0,"iconUrl":"http://content.mqcdn.com/mqsite/turnsigns/icon-dirs-end_sm.gif","direction":0}],"hasFerry":false}],"options":{"arteryWeights":[],"cyclingRoadFactor":1,"timeType":0,"useTraffic":false,"returnLinkDirections":false,"countryBoundaryDisplay":true,"enhancedNarrative":false,"locale":"en_US","tryAvoidLinkIds":[],"drivingStyle":2,"doReverseGeocode":true,"generalize":-1,"mustAvoidLinkIds":[],"sideOfStreetDisplay":true,"routeType":"FASTEST","avoidTimedConditions":false,"routeNumber":0,"shapeFormat":"raw","maxWalkingDistance":-1,"destinationManeuverDisplay":true,"transferPenalty":-1,"narrativeType":"text","walkingSpeed":-1,"urbanAvoidFactor":-1,"stateBoundaryDisplay":true,"unit":"M","highwayEfficiency":22,"maxLinkId":0,"maneuverPenalty":-1,"avoidTripIds":[],"filterZoneFactor":-1,"manmaps":"true"},"locations":[{"dragPoint":false,"displayLatLng":{"lng":16.412134,"lat":48.279816},"adminArea4":"Vienna","adminArea5":"Floridsdorf","postalCode":"","adminArea1":"AT","adminArea3":"VIENNA","type":"s","sideOfStreet":"N","geocodeQualityCode":"A5XAX","adminArea4Type":"County","linkId":84180559,"street":"","adminArea5Type":"City","geocodeQuality":"CITY","adminArea1Type":"Country","adminArea3Type":"State","latLng":{"lng":16.412135,"lat":48.279815}},{"dragPoint":false,"displayLatLng":{"lng":16.45393,"lat":48.246792},"adminArea4":"","adminArea5":"Wien","postalCode":"1220","adminArea1":"AT","adminArea3":"Wien","type":"s","sideOfStreet":"N","geocodeQualityCode":"B3ACA","adminArea4Type":"County","linkId":70179230,"street":"Kagran","adminArea5Type":"City","geocodeQuality":"STREET","adminArea1Type":"Country","adminArea3Type":"State","latLng":{"lng":16.45393,"lat":48.24679}}],"time":699,"hasUnpaved":false,"locationSequence":[0,1],"hasFerry":false},"info":{"statuscode":0,"copyright":{"imageAltText":"© 2021 MapQuest, Inc.","imageUrl":"http://api.mqcdn.com/res/mqlogo.gif","text":"© 2021 MapQuest, Inc."},"messages":[]}}
{"route":{"hasTollRoad":false,"hasBridge":false,"boundingBox":{"lr":{"lng":16.453671,"lat":48.246391},"ul":{"lng":16.402002,"lat":48.2803}},"distance":4.047,"hasTimedRestriction":false,"hasTunnel":false,"hasHighway":false,"computedWaypoints":[],"routeError":{"errorCode":-400,"message":""},"formattedTime":"00:11:39","sessionId":"60684908-029b-4ee4-02b4-351c-12d3cb4bf26b","hasAccessRestriction":false,"realTime":-1,"hasSeasonalClosure":false,"hasCountryCross":false,"fuelUsed":0.24,"legs":[{"hasTollRoad":false,"hasBridge":false,"destNarrative":"Proceed to KAGRAN.","distance":4.047,"hasTimedRestriction":false,"hasTunnel":false,"hasHighway":false,"index":0,"formattedTime":"00:11:39","origIndex":-1,"hasAccessRestriction":false,"hasSeasonalClosure":false,"hasCountryCross":false,"roadGradeStrategy":[[]],"destIndex":4,"time":699,"hasUnpaved":false,"origNarrative":"","maneuvers":[{"distance":0.011,"streets":["B7","Brünner Straße","E461"],"narrative":"Start out going northeast on B7/Brünner Straße/E461 toward Carabelligasse.","turnType":0,"startPoint":{"lng":16.41094,"lat":48.280102},"index":0,"formattedTime":"00:00:01","directionName":"Northeast","maneuverNotes":[],"linkIds":[],"signs":[],"mapUrl":"http://www.mapquestapi.com/staticmap/v5/map?key=V5j8RGvth4UydnpUgMg2RYyVNpE12fJy&size=225,160&locations=48.28010177612305,16.410940170288086|marker-1||48.28024673461914,16.41103172302246|marker-2||&center=48.280174255371094,16.410985946655273&defaultMarker=none&zoom=15&rand=-1852306207&session=60684908-029b-4ee4-02b4-351c-12d3cb4bf26b","transportMode":"AUTO","attributes":0,"time":1,"iconUrl":"http://content.mqcdn.com/mqsite/turnsigns/icon-dirs-start_sm.gif","direction":3},{"distance":0.012,"streets":["Carabelligasse"],"narrative":"Turn left onto Carabelligasse.","turnType":6,"startPoint":{"lng":16.411032,"lat":48.280247},"index":1,"formattedTime":"00:00:16","directionName":"West","maneuverNotes":[],"linkIds":[],"signs":[],"mapUrl":"http://www.mapquestapi.com/staticmap/v5/map?key=V5j8RGvth4UydnpUgMg2RYyVNpE12fJy&size=225,160&locations=48.28024673461914,16.41103172302246|marker-2||48.28030014038086,16.410791397094727|marker-3||&center=48.2802734375,16.410911560058594&defaultMarker=none&zoom=15&rand=-1852306207&session=60684908-029b-4ee4-02b4-351c-12d3cb4bf26b","transportMode":"AUTO","attributes":0,"time":16,"iconUrl":"http://content.mqcdn.com/mqsite/turnsigns/rs_left_sm.gif","direction":7},{"distance":1.125,"streets":["B7","Brünner Straße"],"narrative":"Turn left onto B7/Brünner Straße/E461. Continue to follow B7/Brünner Straße.","turnType":6,"startPoint":{"lng":16.410791,"lat":48.2803},"index":2,"formattedTime":"00:03:05","directionName":"South","maneuverNotes":[],"linkIds":[],"signs":[],"mapUrl":"http://www.mapquestapi.com/staticmap/v5/map?key=V5j8RGvth4UydnpUgMg2RYyVNpE12fJy&size=225,160&locations=48.28030014038086,16.410791397094727|marker-3||48.26513671875,16.402002334594727|marker-4||&center=48.27271842956543,16.406396865844727&defaultMarker=none&zoom=9&rand=-1852306207&session=60684908-029b-4ee4-02b4-351c-12d3cb4bf26b","transportMode":"AUTO","attributes":0,"time":185,"iconUrl":"http://content.mqcdn.com/mqsite/turnsigns/rs_left_sm.gif","direction":4},{"distance":1.55,"streets":["B3"],"narrative":"Turn left onto B3/Katsushikastraße. Continue to follow B3.","turnType":6,"startPoint":{"lng":16.402002,"lat":48.265137},"index":3,"formattedTime":"00:03:30","directionName":"Southeast","maneuverNotes":[],"linkIds":[],"signs":[],"mapUrl":"http://www.mapquestapi.com/staticmap/v5/map?key=V5j8RGvth4UydnpUgMg2RYyVNpE12fJy&size=225,160&locations=48.26513671875,16.402002334594727|marker-4||48.2519645690918,16.427919387817383|marker-5||&center=48.2585506439209,16.414960861206055&defaultMarker=none&zoom=9&rand=-1852306207&session=60684908-029b-4ee4-02b4-351c-12d3cb4bf26b","transportMode":"AUTO","attributes":0,"time":210,"iconUrl":"http://content.mqcdn.com/mqsite/turnsigns/rs_left_sm.gif","direction":5},{"distance":0.73,"streets":["Donaufelder Straße"],"narrative":"Turn left onto Donaufelder Straße.","turnType":6,"startPoint":{"lng":16.427919,"lat":48.251965},"index":4,"formattedTime":"00:02:10","directionName":"East","maneuverNotes":[],"linkIds":[],"signs":[],"mapUrl":"http://www.mapquestapi.com/staticmap/v5/map?key=V5j8RGvth4UydnpUgMg2RYyVNpE12fJy&size=225,160&locations=48.2519645690918,16.427919387817383|marker-5||48.24996566772461,16.443326950073242|marker-6||&center=48.2509651184082,16.435623168945312&defaultMarker=none&zoom=10&rand=-1852306207&session=60684908-029b-4ee4-02b4-351c-12d3cb4bf26b","transportMode":"AUTO","attributes":0,"time":130,"iconUrl":"http://content.mqcdn.com/mqsite/turnsigns/rs_left_sm.gif","direction":8},{"distance":0.395,"streets":["Kagraner Platz"],"narrative":"Donaufelder Straße becomes Kagraner Platz.","turnType":0,"startPoint":{"lng":16.443327,"lat":48.249966},"index":5,"formattedTime":"00:01:02","directionName":"East","maneuverNotes":[],"linkIds":[],"signs":[],"mapUrl":"http://www.mapquestapi.com/staticmap/v5/map?key=V5j8RGvth4UydnpUgMg2RYyVNpE12fJy&size=225,160&locations=48.24996566772461,16.443326950073242|marker-6||48.248291015625,16.451400756835938|marker-7||&center=48.249128341674805,16.44736385345459&defaultMarker=none&zoom=11&rand=-1852306207&session=60684908-029b-4ee4-02b4-351c-12d3cb4bf26b","transportMode":"AUTO","attributes":0,"time":62,"iconUrl":"http://content.mqcdn.com/mqsite/turnsigns/rs_straight_sm.gif","direction":8},{"distance":0.064,"streets":["Zillingergasse"],"narrative":"Turn right onto Zillingergasse.","turnType":2,"startPoint":{"lng":16.451401,"lat":48.248291},"index":6,"formattedTime":"00:00:18","directionName":"Southeast","maneuverNotes":[],"linkIds":[],"signs":[],"mapUrl":"http://www.mapquestapi.com/staticmap/v5/map?key=V5j8RGvth4UydnpUgMg2RYyVNpE12fJy&size=225,160&locations=48.248291015625,16.451400756835938|marker-7||48.247474670410156,16.451570510864258|marker-8||&center=48.24788284301758,16.451485633850098&defaultMarker=none&zoom=14&rand=-1852306207&session=60684908-029b-4ee4-02b4-351c-12d3cb4bf26b","transportMode":"AUTO","attributes":0,"time":18,"iconUrl":"http://content.mqcdn.com/mqsite/turnsigns/rs_right_sm.gif","direction":5},{"distance":0.081,"streets":["Hirschstettner Straße"],"narrative":"Zillingergasse becomes Hirschstettner Straße.","turnType":0,"startPoint":{"lng":16.451571,"lat":48.247475},"index":7,"formattedTime":"00:00:20","directionName":"Southeast","maneuverNotes":[],"linkIds":[],"signs":[],"mapUrl":"http://www.mapquestapi.com/staticmap/v5/map?key=V5j8RGvth4UydnpUgMg2RYyVNpE12fJy&size=225,160&locations=48.247474670410156,16.451570510864258|marker-8||48.24639129638672,16.452171325683594|marker-9||&center=48.24693298339844,16.451870918273926&defaultMarker=none&zoom=13&rand=-1852306207&session=60684908-029b-4ee4-02b4-351c-12d3cb4bf26b","transportMode":"AUTO","attributes":0,"time":20,"iconUrl":"http://content.mqcdn.com/mqsite/turnsigns/rs_straight_sm.gif","direction":5},{"distance":0.079,"streets":[],"narrative":"Turn left.","turnType":6,"startPoint":{"lng":16.452171,"lat":48.246391},"index":8,"formattedTime":"00:00:57","directionName":"East","maneuverNotes":[],"linkIds":[],"signs":[],"mapUrl":"http://www.mapquestapi.com/staticmap/v5/map?key=V5j8RGvth4UydnpUgMg2RYyVNpE12fJy&size=225,160&locations=48.24639129638672,16.452171325683594|marker-9||48.24666213989258,16.453670501708984|marker-10||&center=48.24652671813965,16.45292091369629&defaultMarker=none&zoom=15&rand=-1852306207&session=60684908-029b-4ee4-02b4-351c-12d3cb4bf26b","transportMode":"AUTO","attributes":0,"time":57,"iconUrl":"http://content.mqcdn.com/mqsite/turnsigns/rs_left_sm.gif","direction":8},{"distance":0,"streets":[],"narrative":"KAGRAN.","turnType":-1,"startPoint":{"lng":16.453671,"lat":48.246662},"index":9,"formattedTime":"00:00:00","directionName":"","maneuverNotes":[],"linkIds":[],"signs":[],"transportMode":"AUTO","attributes":0,"time":0,"iconUrl":"http://content.mqcdn.com/mqsite/turnsigns/icon-dirs-end_sm.gif","direction":0}],"hasFerry":false}],"options":{"arteryWeights":[],"cyclingRoadFactor":1,"timeType":0,"useTraffic":false,"returnLinkDirections":false,"countryBoundaryDisplay":true,"enhancedNarrative":false,"locale":"en_US","tryAvoidLinkIds":[],"drivingStyle":2,"doReverseGeocode":true,"generalize":-1,"mustAvoidLinkIds":[],"sideOfStreetDisplay":true,"routeType":"FASTEST","avoidTimedConditions":false,"routeNumber":0,"shapeFormat":"raw","maxWalkingDistance":-1,"destinationManeuverDisplay":true,"transferPenalty":-1,"narrativeType":"text","walkingSpeed":-1,"urbanAvoidFactor":-1,"stateBoundaryDisplay":true,"unit":"M","highwayEfficiency":22,"maxLinkId":0,"maneuverPenalty":-1,"avoidTripIds":[],"filterZoneFactor":-1,"manmaps":"true"},"locations":[{"dragPoint":false,"displayLatLng":{"lng":16.412134,"lat":48.279816},"adminArea4":"Vienna","adminArea5":"Floridsdorf","postalCode":"","adminArea1":"AT","adminArea3":"VIENNA","type":"s","sideOfStreet":"N","geocodeQualityCode":"A5XAX","adminArea4Type":"County","linkId":84180559,"street":"","adminArea5Type":"City","geocodeQuality":"CITY","adminArea1Type":"Country","adminArea3Type":"State","latLng":{"lng":16.412135,"lat":48.279815}},{"dragPoint":false,"displayLatLng":{"lng":16.45393,"lat":48.246792},"adminArea4":"","adminArea5":"Wien","postalCode":"1220","adminArea1":"AT","adminArea3":"Wien","type":"s","sideOfStreet":"N","geocodeQualityCode":"B3ACA","adminArea4Type":"County","linkId":70179230,"street":"Kagran","adminArea5Type":"City","geocodeQuality":"STREET","adminArea1Type":"Country","adminArea3Type":"State","latLng":{"lng":16.45393,"lat":48.24679}}],"time":699,"hasUnpaved":false,"locationSequence":[0,1],"hasFerry":false},"info":{"statuscode":0,"copyright":{"imageAltText":"© 2021 MapQuest, Inc.","imageUrl":"http://api.mqcdn.com/res/mqlogo.gif","text":"© 2021 MapQuest, Inc."},"messages":[]}}